django_input_mask-2.0.2.dist-info/DESCRIPTION.rst
django_input_mask-2.0.2.dist-info/LICENSE.txt
django_input_mask-2.0.2.dist-info/METADATA
django_input_mask-2.0.2.dist-info/metadata.json
django_input_mask-2.0.2.dist-info/RECORD
django_input_mask-2.0.2.dist-info/top_level.txt
django_input_mask-2.0.2.dist-info/WHEEL
input_mask/__init__.py
input_mask/fields.py
input_mask/tests.py
input_mask/utils.py
input_mask/widgets.py
input_mask/contrib/__init__.py
input_mask/contrib/localflavor/__init__.py
input_mask/contrib/localflavor/br/__init__.py
input_mask/contrib/localflavor/br/fields.py
input_mask/contrib/localflavor/br/widgets.py
input_mask/contrib/localflavor/us/__init__.py
input_mask/contrib/localflavor/us/fields.py
input_mask/contrib/localflavor/us/widgets.py
input_mask/static/input_mask/js/jquery.maskedinput.min.js
input_mask/static/input_mask/js/jquery.maskMoney.min.js
input_mask/static/input_mask/js/text_input_mask.js
tests/__init__.py
tests/forms.py
tests/test.py
tests/test_settings.py
