Metadata-Version: 1.1
Name: django-input-mask
Version: 2.0.2
Summary: JavaScript input masks for Django
Home-page: http://github.com/caioariede/django-input-mask
Author: Caio Ariede
Author-email: caio.ariede@gmail.com
License: MIT
Platform: any
Classifier: Development Status :: 5 - Production/Stable
Classifier: Environment :: Web Environment
Classifier: Intended Audience :: Developers
Classifier: License :: OSI Approved :: MIT License
Classifier: Natural Language :: English
Classifier: Operating System :: OS Independent
Classifier: Framework :: Django
Classifier: Programming Language :: Python
Classifier: Programming Language :: Python :: 3
Classifier: Programming Language :: Python :: 3.4
Classifier: Programming Language :: Python :: Implementation :: PyPy
